vlbiplanobs/__init__.py
vlbiplanobs/cli.py
vlbiplanobs/constraints.py
vlbiplanobs/freqsetups.py
vlbiplanobs/observation.py
vlbiplanobs/rfc.py
vlbiplanobs/scheduler.py
vlbiplanobs/sources.py
vlbiplanobs/stations.py
vlbiplanobs/data/.DS_Store
vlbiplanobs/data/__init__.py
vlbiplanobs/data/finals2000A.all
vlbiplanobs/data/network_catalog.inp
vlbiplanobs/data/rfc_2021c_cat.txt
vlbiplanobs/data/stations_catalog.inp
vlbiplanobs/gui/__init__.py
vlbiplanobs/gui/callbacks.py
vlbiplanobs/gui/inputs.py
vlbiplanobs/gui/layout.py
vlbiplanobs/gui/main.py
vlbiplanobs/gui/outputs.py
vlbiplanobs/gui/plots.py
vlbiplanobs/gui/assets/.DS_Store
vlbiplanobs/gui/assets/EVN.jpg
vlbiplanobs/gui/assets/ant-alesund.jpg
vlbiplanobs/gui/assets/ant-alma.jpg
vlbiplanobs/gui/assets/ant-apex.jpg
vlbiplanobs/gui/assets/ant-arecibo.jpg
vlbiplanobs/gui/assets/ant-arecibo_12m.jpg
vlbiplanobs/gui/assets/ant-aro12m.jpg
vlbiplanobs/gui/assets/ant-askap.jpg
vlbiplanobs/gui/assets/ant-atca.jpg
vlbiplanobs/gui/assets/ant-badary.jpg
vlbiplanobs/gui/assets/ant-brewster.jpg
vlbiplanobs/gui/assets/ant-cambridge.jpg
vlbiplanobs/gui/assets/ant-ceduna.jpg
vlbiplanobs/gui/assets/ant-darnhall.jpg
vlbiplanobs/gui/assets/ant-defford.jpg
vlbiplanobs/gui/assets/ant-dwingeloo.jpg
vlbiplanobs/gui/assets/ant-effelsberg.jpg
vlbiplanobs/gui/assets/ant-fast.jpg
vlbiplanobs/gui/assets/ant-fort_davis.jpg
vlbiplanobs/gui/assets/ant-gifu.jpg
vlbiplanobs/gui/assets/ant-gmrt.jpg
vlbiplanobs/gui/assets/ant-green_bank.jpg
vlbiplanobs/gui/assets/ant-greenland.jpg
vlbiplanobs/gui/assets/ant-hancock.jpg
vlbiplanobs/gui/assets/ant-hartebeesthoek.jpg
vlbiplanobs/gui/assets/ant-haystack.jpg
vlbiplanobs/gui/assets/ant-hitachi.jpg
vlbiplanobs/gui/assets/ant-hobart.jpg
vlbiplanobs/gui/assets/ant-hobart_12m.jpg
vlbiplanobs/gui/assets/ant-iar_30m.jpg
vlbiplanobs/gui/assets/ant-irbene.jpg
vlbiplanobs/gui/assets/ant-iriki.jpg
vlbiplanobs/gui/assets/ant-ishigaki-jima.jpg
vlbiplanobs/gui/assets/ant-jcmt.jpg
vlbiplanobs-4.6.1.dist-info/licenses/LICENSE
vlbiplanobs-4.6.1.dist-info/METADATA
vlbiplanobs-4.6.1.dist-info/WHEEL
vlbiplanobs-4.6.1.dist-info/entry_points.txt
vlbiplanobs-4.6.1.dist-info/top_level.txt
vlbiplanobs-4.6.1.dist-info/RECORD
