Metadata-Version: 2.4
Name: vlbiplanobs
Version: 4.6.1
Summary: Observaiton Planner for VLBI observations
Author-email: "B. Marcote" <marcote@jive.eu>
License-Expression: GPL-3.0-or-later
Project-URL: Bug Reports, https://github.com/bmarcote/vlbi_calculator/issues
Project-URL: Source, https://github.com/bmarcote/vlbi_calculator/
Keywords: astronomy,astrophysics,cosmology,radio,science,observations,planner,coordinate
Classifier: Development Status :: 4 - Beta
Classifier: Intended Audience :: Science/Research
Classifier: Topic :: Scientific/Engineering :: Astronomy
Classifier: Programming Language :: Python :: 3
Classifier: Programming Language :: Python :: 3.7
Classifier: Programming Language :: Python :: 3.8
Classifier: Programming Language :: Python :: 3 :: Only
Requires-Python: >=3.11
License-File: LICENSE
Requires-Dist: six
Requires-Dist: numpy
Requires-Dist: astropy>=4.0.2
Requires-Dist: astroplan>=0.7
Requires-Dist: rich
Requires-Dist: rich_argparse
Requires-Dist: plotext
Requires-Dist: matplotlib
Requires-Dist: plotly
Requires-Dist: dash>=3.0
Requires-Dist: dash-bootstrap-components>=2.0
Requires-Dist: dash-mantine-components
Requires-Dist: kaleido
Requires-Dist: loguru
Requires-Dist: borb
Dynamic: license-file
